DB_helper/__init__.py
DB_helper-1.1.0.dist-info/METADATA
DB_helper-1.1.0.dist-info/WHEEL
DB_helper-1.1.0.dist-info/top_level.txt
DB_helper-1.1.0.dist-info/RECORD
