Metadata-Version: 2.1
Name: DB-helper
Version: 1.1.0
Summary: Модуль для простого использования БД Sqlite3
Home-page: UNKNOWN
Author: lioppp
Author-email: stroganov400@gmail.com
License: UNKNOWN
Platform: UNKNOWN
Classifier: Programming Language :: Python :: 3
Classifier: Operating System :: OS Independent
Requires-Python: >=3.6
